Metadata-Version: 2.4
Name: llama-index-readers-couchbase
Version: 0.4.1
Summary: llama-index readers couchbase integration
Author-email: Your Name <you@example.com>
Maintainer: nithishr
License-Expression: MIT
License-File: LICENSE
Keywords: Capella,Couchbase,NoSQL
Requires-Python: <4.0,>=3.9
Requires-Dist: couchbase<5,>=4.1.11
Requires-Dist: llama-index-core<0.15,>=0.13.0
